django_scientific-0.0.3.dist-info/DESCRIPTION.rst
django_scientific-0.0.3.dist-info/METADATA
django_scientific-0.0.3.dist-info/RECORD
django_scientific-0.0.3.dist-info/WHEEL
django_scientific-0.0.3.dist-info/metadata.json
django_scientific-0.0.3.dist-info/top_level.txt
djsci/__init__.py
djsci/admin.py
djsci/drf_fields.py
djsci/fields.py
djsci/models.py
djsci/serialize_utils.py
djsci/migrations/0001_initial.py
djsci/migrations/0002_variable_preview.py
djsci/migrations/__init__.py
djsci/tests/__init__.py
djsci/tests/test_fields.py
